[
  {
    "id": 6,
    "title": "The Need to Read",
    "title_zh": "阅读的必要性",
    "source": "Paul Graham",
    "link": "http://www.paulgraham.com/read.html",
    "tags": [
      "learning",
      "communication",
      "thinking"
    ],
    "tags_zh": [
      "阅读",
      "写作",
      "思考"
    ],
    "date": "2025-08-16",
    "summary_en": "The author argues that reading is essential not only for acquiring knowledge but also for developing the ability to write well. Writing is not just a means of conveying ideas but also a way to generate them. Complex and ill-defined problems often require writing for effective solving. Therefore, reading good content is crucial for both writing well and thinking effectively.",
    "summary_zh": "作者认为，阅读不仅是获取知识的必要途径，也是培养良好写作能力的关键。写作不仅仅是传达思想的方式，更是产生思想的方式。复杂和不明确的问题通常需要通过写作来有效解决。因此，阅读优秀的内容对于写好文章和有效思考至关重要。",
    "best_quote_en": "Writing is not just a way to convey ideas, but also a way to have them.",
    "best_quote_zh": "写作不仅仅是传达思想的方式，更是产生思想的方式。"
  }
]